PyComps/LaminateCalculator.py
PyComps/Micromechanics.py
PyComps/__init__.py
PyComps-0.3.2.dist-info/LICENSE
PyComps-0.3.2.dist-info/METADATA
PyComps-0.3.2.dist-info/WHEEL
PyComps-0.3.2.dist-info/top_level.txt
PyComps-0.3.2.dist-info/RECORD
