Metadata-Version: 2.1
Name: PyComps
Version: 0.3.2
Summary: A sample Python package
Home-page: https://github.com/edo-147/PyComp
Author: Edoardo Mancini
Author-email: edoardo.mancini0@gmail.com
Classifier: License :: OSI Approved :: MIT License
License-File: LICENSE
